[
    {
        "id": "29587",
        "name": "4.1.05-piedrasteheran",
        "url": "https://moodle.org/plugins/download.php/29587/format_onetopic_moodle27_2014050305.zip"
    },
    {
        "id": "27361",
        "name": "3.11.04-la-almeria",
        "url": "https://moodle.org/plugins/download.php/27361/format_onetopic_moodle30_2022011117.zip"
    },
    {
        "id": "25540",
        "name": "la-almeria",
        "url": "https://moodle.org/plugins/download.php/25540/format_onetopic_moodle34_2011020704.zip"
    },
    {
        "id": "20808",
        "name": "san-juan",
        "url": "https://moodle.org/plugins/download.php/20808/format_onetopic_moodle26_2014070715.zip"
    },
    {
        "id": "13804",
        "name": "buenavista",
        "url": "https://moodle.org/plugins/download.php/13804/format_onetopic_moodle36_2019060206.zip"
    },
    {
        "id": "10471",
        "name": "las-brisas",
        "url": "https://moodle.org/plugins/download.php/10471/format_onetopic_moodle30_2023010216.zip"
    },
    {
        "id": "8571",
        "name": "la-madera",
        "url": "https://moodle.org/plugins/download.php/8571/format_onetopic_moodle35_2014090512.zip"
    },
    {
        "id": "8569",
        "name": "las-teresas",
        "url": "https://moodle.org/plugins/download.php/8569/format_onetopic_moodle35_2015090219.zip"
    },
    {
        "id": "6970",
        "name": "chuscalito",
        "url": "https://moodle.org/plugins/download.php/6970/format_onetopic_moodle33_2021050101.zip"
    },
    {
        "id": "6969",
        "name": "mazorcal",
        "url": "https://moodle.org/plugins/download.php/6969/format_onetopic_moodle26_2011041106.zip"
    },
    {
        "id": "3329",
        "name": "chalarca",
        "url": "https://moodle.org/plugins/download.php/3329/format_onetopic_moodle36_2016070501.zip"
    },
    {
        "id": "2411",
        "name": "pantalio",
        "url": "https://moodle.org/plugins/download.php/2411/format_onetopic_moodle37_2014030318.zip"
    },
    {
        "id": "1722",
        "name": "guarango",
        "url": "https://moodle.org/plugins/download.php/1722/format_onetopic_moodle39_2012100515.zip"
    },
    {
        "id": "548",
        "name": "2012021301",
        "url": "https://moodle.org/plugins/download.php/548/format_onetopic_moodle26_2010071002.zip"
    },
    {
        "id": "325",
        "name": "2011030101",
        "url": "https://moodle.org/plugins/download.php/325/format_onetopic_moodle32_2012070605.zip"
    },
    {
        "id": "114",
        "name": "2011030100",
        "url": "https://moodle.org/plugins/download.php/114/format_onetopic_moodle32_2013050305.zip"
    },
    {
        "id": "28900",
        "name": "4.1.04-piedrasteheran",
        "url": "https://moodle.org/plugins/download.php/28900/format_onetopic_moodle32_2015030212.zip"
    },
    {
        "id": "28431",
        "name": "4.1.03-piedrasteheran",
        "url": "https://moodle.org/plugins/download.php/28431/format_onetopic_moodle33_2023120607.zip"
    },
    {
        "id": "28397",
        "name": "4.1.1-piedrasteheran",
        "url": "https://moodle.org/plugins/download.php/28397/format_onetopic_moodle27_2014020210.zip"
    },
    {
        "id": "27619",
        "name": "4.0.1-piedrasteheran",
        "url": "https://moodle.org/plugins/download.php/27619/format_onetopic_moodle30_2013090906.zip"
    }
]