{
    "id": 961,
    "index": 113,
    "name": "Subcourse",
    "frankenstyle": "mod_subcourse",
    "plugintype": {
        "type": "mod",
        "name": "Activity module"
    },
    "approved": 1,
    "url": "https://moodle.org/plugins/mod_subcourse",
    "shortdescription": "Subcourse behaves as a graded activity. The grade for each student is automatically fetched from a final grade in another course. This allows course designers to organize the learning content into separate units.",
    "timelastreleased": {
        "absdate": "Thursday, 5 August 2021, 3:27 PM",
        "reldate": "24 months",
        "iso8601date": "2021-08-05T15:27:25+08:00"
    },
    "aggsites": "2921",
    "aggdownloads": "1k",
    "aggfavs": "161",
    "has_logo": true,
    "logo": {
        "tinyicon": "https://moodle.org/pluginfile.php/50/local_plugins/plugin_logo/961/icon.png?preview=tinyicon",
        "thumb": "https://moodle.org/pluginfile.php/50/local_plugins/plugin_logo/961/icon.png?preview=thumb"
    },
    "has_screenshots": true,
    "mainscreenshot": {
        "bigthumb": "https://moodle.org/pluginfile.php/50/local_plugins/plugin_screenshots/961/schema-subcourse.png?preview=bigthumb"
    },
    "screenshots": [
        {
            "bigthumb": "https://moodle.org/pluginfile.php/50/local_plugins/plugin_screenshots/961/master-outline.png?preview=bigthumb"
        },
        {
            "bigthumb": "https://moodle.org/pluginfile.php/50/local_plugins/plugin_screenshots/961/mobile_view.png?preview=bigthumb"
        },
        {
            "bigthumb": "https://moodle.org/pluginfile.php/50/local_plugins/plugin_screenshots/961/settings-completion.png?preview=bigthumb"
        },
        {
            "bigthumb": "https://moodle.org/pluginfile.php/50/local_plugins/plugin_screenshots/961/settings-refcourse.png?preview=bigthumb"
        },
        {
            "bigthumb": "https://moodle.org/pluginfile.php/50/local_plugins/plugin_screenshots/961/view-student.png?preview=bigthumb"
        },
        {
            "bigthumb": "https://moodle.org/pluginfile.php/50/local_plugins/plugin_screenshots/961/view-teacher.png?preview=bigthumb"
        }
    ],
    "maintainers": [
        {
            "id": 1601,
            "firstname": "David",
            "lastname": "Mudr\u00e1k",
            "url": "https://moodle.org/user/profile.php?id=1601"
        }
    ],
    "descriptors": [
        {
            "descriptorid": 1,
            "value": "Assessment"
        }
    ]
}