{
    "id": 431,
    "index": 1534,
    "name": "External zip utility",
    "frankenstyle": "local_externalzip",
    "plugintype": {
        "type": "local",
        "name": "Local plugin"
    },
    "approved": 1,
    "url": "https://moodle.org/plugins/local_externalzip",
    "shortdescription": "Allows Moodle to use the command-line zip utility (/usr/bin/zip) instead of the PHP ZipArchive library.",
    "timelastreleased": {
        "absdate": "Wednesday, 17 July 2013, 7:24 AM",
        "reldate": "10 years",
        "iso8601date": "2013-07-17T07:24:08+08:00"
    },
    "aggsites": "33",
    "aggdownloads": "10",
    "aggfavs": "2",
    "has_logo": false,
    "logo": {
        "tinyicon": null,
        "thumb": null
    },
    "has_screenshots": null,
    "mainscreenshot": {
        "bigthumb": "https://moodle.org/theme/image.php/moodleorg/local_plugins/1688119780/screenshotmissing"
    },
    "screenshots": [],
    "maintainers": [
        {
            "id": 1070092,
            "firstname": "Aaron",
            "lastname": "Wells",
            "url": "https://moodle.org/user/profile.php?id=1070092"
        }
    ],
    "descriptors": [
        {
            "descriptorid": 2,
            "value": "Administrator"
        }
    ]
}